playwright_sm-0.0.1.dist-info/licenses/LICENSE
playwright_stealth/__init__.py
playwright_stealth/stealth.py
playwright_stealth/js/chrome.app.js
playwright_stealth/js/chrome.csi.js
playwright_stealth/js/chrome.hairline.js
playwright_stealth/js/chrome.load.times.js
playwright_stealth/js/chrome.runtime.js
playwright_stealth/js/generate.magic.arrays.js
playwright_stealth/js/iframe.contentWindow.js
playwright_stealth/js/media.codecs.js
playwright_stealth/js/navigator.hardwareConcurrency.js
playwright_stealth/js/navigator.languages.js
playwright_stealth/js/navigator.permissions.js
playwright_stealth/js/navigator.platform.js
playwright_stealth/js/navigator.plugins.js
playwright_stealth/js/navigator.userAgent.js
playwright_stealth/js/navigator.userAgentData.js
playwright_stealth/js/navigator.vendor.js
playwright_stealth/js/navigator.webdriver.js
playwright_stealth/js/utils.js
playwright_stealth/js/webgl.vendor.js
playwright_stealth/js/window.outerdimensions.js
tests/__init__.py
playwright_sm-0.0.1.dist-info/METADATA
playwright_sm-0.0.1.dist-info/WHEEL
playwright_sm-0.0.1.dist-info/top_level.txt
playwright_sm-0.0.1.dist-info/RECORD
