Metadata-Version: 2.4
Name: playwright-sm
Version: 0.0.1
Summary: playwright stealth
Home-page: https://github.com/MaxxRK/playwright_stealth
Author: AtuboDad
Author-email: maxxrk@pm.me
Classifier: Programming Language :: Python :: 3
Classifier: License :: OSI Approved :: MIT License
Classifier: Operating System :: OS Independent
Requires-Python: >=3.10
License-File: LICENSE
Requires-Dist: playwright==1.52.0
Provides-Extra: test
Requires-Dist: pytest; extra == "test"
Dynamic: author
Dynamic: author-email
Dynamic: classifier
Dynamic: description
Dynamic: description-content-type
Dynamic: home-page
Dynamic: license-file
Dynamic: provides-extra
Dynamic: requires-dist
Dynamic: requires-python
Dynamic: summary
